django_jsx/__init__.py
django_jsx/management/__init__.py
django_jsx/management/commands/__init__.py
django_jsx/management/commands/compilejsx.py
django_jsx/templatetags/__init__.py
django_jsx/templatetags/jsx.py
django_jsx-0.3.0.dist-info/DESCRIPTION.rst
django_jsx-0.3.0.dist-info/METADATA
django_jsx-0.3.0.dist-info/RECORD
django_jsx-0.3.0.dist-info/WHEEL
django_jsx-0.3.0.dist-info/metadata.json
django_jsx-0.3.0.dist-info/top_level.txt
tests/__init__.py
tests/test_compilejsx.py
tests/test_jsx_tag.py
tests/test_serialize.py
tests/test_settings.py
tests/test_template_files.py
