Metadata-Version: 2.0
Name: django-jsx
Version: 0.3.0
Summary: Integration library for React/JSX and Django
Home-page: UNKNOWN
Author: Calvin Spealman
Author-email: calvin@caktusgroup.com
License: BSD
Platform: UNKNOWN
Classifier: Topic :: Internet :: WWW/HTTP :: Dynamic Content
Classifier: Intended Audience :: Developers
Classifier: License :: OSI Approved :: BSD License
Classifier: Programming Language :: Python
